emploid/beholder.py
emploid/constants.py
emploid/emploid.py
emploid/portman.py
emploid/record.py
emploid/scribe.py
emploid/taskman.py
emploid/testman.py
emploid/tools.py
emploid-0.4.9.dist-info/LICENSE
emploid-0.4.9.dist-info/METADATA
emploid-0.4.9.dist-info/WHEEL
emploid-0.4.9.dist-info/top_level.txt
emploid-0.4.9.dist-info/RECORD
