Metadata-Version: 2.1
Name: emploid
Version: 0.4.9
Summary: A simple to use automation tool for automating web, android and windows proccesses.
Author: PixQuilly
Author-email: pixquilly@gmail.com
License-File: LICENSE
Requires-Dist: numpy
Requires-Dist: opencv-python
Requires-Dist: requests
Requires-Dist: Appium-Python-Client
Requires-Dist: mysql-connector-python
Requires-Dist: PyAutoGUI
Requires-Dist: selenium
Requires-Dist: pyodbc
